logparser/__init__.py
logparser/__version__.py
logparser/common.py
logparser/logparser.py
logparser/run.py
logparser/scrapylogparser.py
logparser/settings.py
logparser/telnet.py
logparser/utils.py
logparser-0.8.4.dist-info/LICENSE
logparser-0.8.4.dist-info/METADATA
logparser-0.8.4.dist-info/WHEEL
logparser-0.8.4.dist-info/entry_points.txt
logparser-0.8.4.dist-info/top_level.txt
logparser-0.8.4.dist-info/RECORD
